efaciency/__init__.py
efaciency/block.py
efaciency/cli.py
efaciency/sp.py
efaciency/utils.py
efaciency-0.4.0.dist-info/entry_points.txt
efaciency-0.4.0.dist-info/licenses/LICENSE
efaciency-0.4.0.dist-info/WHEEL
efaciency-0.4.0.dist-info/METADATA
efaciency-0.4.0.dist-info/RECORD
