Metadata-Version: 2.4
Name: efaciency
Version: 0.4.0
Summary: An easy way to nagivate EFA blocks and settlement periods in GB electricity trading.
Author: Matthieu Paturet
Requires-Python: >=3.10
Classifier: License :: OSI Approved :: MIT License
License-File: LICENSE
Requires-Dist: tzdata
Project-URL: Homepage, https://github.com/capcir/efaciency
